askhelmut/__init__.py
askhelmut/cli.py
askhelmut/constants.py
askhelmut/service.py
askhelmut-0.0.4.dist-info/METADATA
askhelmut-0.0.4.dist-info/WHEEL
askhelmut-0.0.4.dist-info/entry_points.txt
askhelmut-0.0.4.dist-info/licenses/LICENSE
askhelmut-0.0.4.dist-info/RECORD
