Metadata-Version: 2.4
Name: askhelmut
Version: 0.0.4
Summary: 🤖 Exploration.
Project-URL: Homepage, https://askhelmut.readthedocs.io/en/latest/
Project-URL: Documentation, https://askhelmut.readthedocs.io/en/latest/
Project-URL: Source, https://github.com/helmut-hoffer-von-ankershoffen/askhelmut
Project-URL: Changelog, https://github.com/helmut-hoffer-von-ankershoffen/askhelmut/releases
Project-URL: Issues, https://github.com/helmut-hoffer-von-ankershoffen/askhelmut/issues
Author-email: Helmut Hoffer von Ankershoffen <helmuthva@googlemail.com>
License: MIT License
License-File: LICENSE
Keywords: act,askhelmut,codecov,copier,cyclonedx,detect-secrets,devcontainer,docker,git-cliff,jupyter,marimo,mypy,nox,oe-python-template,pip-audit,pip-licenses,pre-commit,pydantic,pypi,pytest,python,readthedocs,ruff,sonarcloud,sonarqube,sphinx,streamlit,typer,uv
Classifier: Development Status :: 2 - Pre-Alpha
Classifier: Framework :: Pydantic
Classifier: Framework :: Pytest
Classifier: Intended Audience :: Developers
Classifier: Intended Audience :: End Users/Desktop
Classifier: License :: OSI Approved :: MIT License
Classifier: Natural Language :: English
Classifier: Operating System :: MacOS :: MacOS X
Classifier: Operating System :: Microsoft :: Windows
Classifier: Operating System :: POSIX :: Linux
Classifier: Programming Language :: Python
Classifier: Programming Language :: Python :: 3
Classifier: Programming Language :: Python :: 3.11
Classifier: Programming Language :: Python :: 3.12
Classifier: Programming Language :: Python :: 3.13
Classifier: Typing :: Typed
Requires-Python: <4.0,>=3.11
Requires-Dist: pydantic>=2.10.6
Requires-Dist: python-dotenv>=1.0.1
Requires-Dist: typer>=0.15.1
Provides-Extra: examples
Requires-Dist: jinja2>=3.1.6; extra == 'examples'
Requires-Dist: jupyter>=1.1.1; extra == 'examples'
Requires-Dist: marimo>=0.11.17; extra == 'examples'
Requires-Dist: streamlit>=1.43.1; extra == 'examples'
